englishtobengali/New Text Document.py
englishtobengali/__init__.py
englishtobengali/entobn.py
englishtobengali/tst.py
englishtobengali-0.0.2.dist-info/LICENSE.txt
englishtobengali-0.0.2.dist-info/METADATA
englishtobengali-0.0.2.dist-info/WHEEL
englishtobengali-0.0.2.dist-info/top_level.txt
englishtobengali-0.0.2.dist-info/RECORD
