Metadata-Version: 2.1
Name: englishtobengali
Version: 0.0.2
Summary: +8801670105219
Home-page: https://github.com/jabedparadox
Author: Md Jabed Ali (Jabed)
Author-email: Jabed.akcc@gmail.com
License: MIT
Keywords: python bangla english translator python english to bangla translator python bangla
Platform: UNKNOWN
Classifier: Operating System :: OS Independent
Classifier: Programming Language :: Python :: 2.7
Classifier: Programming Language :: Python :: 3.3
Classifier: Programming Language :: Python :: 3.4
Classifier: Programming Language :: Python :: 3.5
Classifier: Programming Language :: Python :: 3.6
Classifier: Intended Audience :: Developers
Classifier: License :: OSI Approved :: MIT License
Classifier: Development Status :: 5 - Production/Stable
Classifier: Topic :: Software Development :: Libraries :: Python Modules
